noapi/__init__.py
noapi/main.py
noapi/connector/__init__.py
noapi/connector/client.py
noapi/connector/server.py
noapi/objects/__init__.py
noapi/objects/local.py
noapi/objects/models.py
noapi/objects/remote.py
NoApi-0.9.dist-info/METADATA
NoApi-0.9.dist-info/WHEEL
NoApi-0.9.dist-info/top_level.txt
NoApi-0.9.dist-info/RECORD
